CreatePackage/__init__.py
CreatePackage/asgi.py
CreatePackage/settings.py
CreatePackage/urls.py
CreatePackage/wsgi.py
rabbiCalculator/__init__.py
rabbiCalculator-0.1.dist-info/LICENCE.txt
rabbiCalculator-0.1.dist-info/METADATA
rabbiCalculator-0.1.dist-info/WHEEL
rabbiCalculator-0.1.dist-info/top_level.txt
rabbiCalculator-0.1.dist-info/RECORD
