Metadata-Version: 2.1
Name: rabbiCalculator
Version: 0.1
Summary: use for calculate two value
Author: fazle rabbi
Author-email: fazlerabbi2248@gmail.com
Classifier: Programming Language :: Python :: 3
Classifier: License :: OSI Approved :: MIT License
Classifier: Operating System :: OS Independent
License-File: LICENCE.txt
